setup.cfg
setup.py
rasa_nlu/__init__.py
rasa_nlu/components.py
rasa_nlu/config.py
rasa_nlu/convert.py
rasa_nlu/converters.py
rasa_nlu/data_router.py
rasa_nlu/download.py
rasa_nlu/model.py
rasa_nlu/persistor.py
rasa_nlu/registry.py
rasa_nlu/server.py
rasa_nlu/train.py
rasa_nlu/training_data.py
rasa_nlu/version.py
rasa_nlu/wsgi.py
rasa_nlu/classifiers/__init__.py
rasa_nlu/classifiers/keyword_intent_classifier.py
rasa_nlu/classifiers/mitie_intent_classifier.py
rasa_nlu/classifiers/sklearn_intent_classifier.py
rasa_nlu/emulators/__init__.py
rasa_nlu/emulators/api.py
rasa_nlu/emulators/luis.py
rasa_nlu/emulators/wit.py
rasa_nlu/extractors/__init__.py
rasa_nlu/extractors/crf_entity_extractor.py
rasa_nlu/extractors/duckling_extractor.py
rasa_nlu/extractors/entity_synonyms.py
rasa_nlu/extractors/mitie_entity_extractor.py
rasa_nlu/extractors/spacy_entity_extractor.py
rasa_nlu/featurizers/__init__.py
rasa_nlu/featurizers/mitie_featurizer.py
rasa_nlu/featurizers/ngram_featurizer.py
rasa_nlu/featurizers/spacy_featurizer.py
rasa_nlu/tokenizers/__init__.py
rasa_nlu/tokenizers/mitie_tokenizer.py
rasa_nlu/tokenizers/spacy_tokenizer.py
rasa_nlu/tokenizers/whitespace_tokenizer.py
rasa_nlu/utils/__init__.py
rasa_nlu/utils/mitie_utils.py
rasa_nlu/utils/spacy_utils.py
rasa_nlu_latest.egg-info/PKG-INFO
rasa_nlu_latest.egg-info/SOURCES.txt
rasa_nlu_latest.egg-info/dependency_links.txt
rasa_nlu_latest.egg-info/requires.txt
rasa_nlu_latest.egg-info/top_level.txt