Metadata-Version: 1.1
Name: rasa-nlu-latest
Version: 0.8.0a10
Summary: rasa NLU a natural language parser for bots
Home-page: https://rasa.ai
Author: Alan Nichol
Author-email: alan@golastmile.com
License: UNKNOWN
Download-URL: https://github.com/golastmile/rasa_nlu/archive/0.8.0a10.tar.gz
Keywords: NLP,bots
Platform: UNKNOWN
Classifier: Programming Language :: Python :: 2.7
Classifier: Programming Language :: Python :: 3.4
Classifier: Programming Language :: Python :: 3.5
Classifier: Programming Language :: Python :: 3.6
